{
	"info": {
		"_postman_id": "tasklist-api-collection",
		"name": "Tasklist API",
		"description": "Collection completa da API Tasklist com autenticação JWT",
		"schema": "https://schema.getpostman.com/json/collection/v2.1.0/collection.json"
	},
	"auth": {
		"type": "bearer",
		"bearer": [
			{
				"key": "token",
				"value": "{{accessToken}}",
				"type": "string"
			}
		]
	},
	"item": [
		{
			"name": "Authentication",
			"item": [
				{
					"name": "Register User",
					"event": [
						{
							"listen": "test",
							"script": {
								"exec": [
									"if (pm.response.code === 200 || pm.response.code === 201) {",
									"    var jsonData = pm.response.json();",
									"    if (jsonData.accessToken) {",
									"        pm.collectionVariables.set(\"accessToken\", jsonData.accessToken);",
									"        pm.collectionVariables.set(\"refreshToken\", jsonData.refreshToken);",
									"    }",
									"}"
								],
								"type": "text/javascript"
							}
						}
					],
					"request": {
						"auth": {
							"type": "noauth"
						},
						"method": "POST",
						"header": [
							{
								"key": "Content-Type",
								"value": "application/json"
							}
						],
						"body": {
							"mode": "raw",
							"raw": "{\n    \"name\": \"John Doe\",\n    \"email\": \"john.doe@example.com\",\n    \"password\": \"password123\"\n}"
						},
						"url": {
							"raw": "{{baseUrl}}/api/v1/auth/register",
							"host": [
								"{{baseUrl}}"
							],
							"path": [
								"api",
								"v1",
								"auth",
								"register"
							]
						},
						"description": "Registra um novo usuário no sistema"
					},
					"response": []
				},
				{
					"name": "Login",
					"event": [
						{
							"listen": "test",
							"script": {
								"exec": [
									"if (pm.response.code === 200) {",
									"    var jsonData = pm.response.json();",
									"    pm.collectionVariables.set(\"accessToken\", jsonData.accessToken);",
									"    pm.collectionVariables.set(\"refreshToken\", jsonData.refreshToken);",
									"    pm.collectionVariables.set(\"userId\", jsonData.user.id);",
									"    console.log(\"Token salvo: \" + jsonData.accessToken);",
									"}"
								],
								"type": "text/javascript"
							}
						}
					],
					"request": {
						"auth": {
							"type": "noauth"
						},
						"method": "POST",
						"header": [
							{
								"key": "Content-Type",
								"value": "application/json"
							}
						],
						"body": {
							"mode": "raw",
							"raw": "{\n    \"email\": \"john.doe@example.com\",\n    \"password\": \"password123\"\n}"
						},
						"url": {
							"raw": "{{baseUrl}}/api/v1/auth/login",
							"host": [
								"{{baseUrl}}"
							],
							"path": [
								"api",
								"v1",
								"auth",
								"login"
							]
						},
						"description": "Autentica um usuário e retorna tokens JWT"
					},
					"response": []
				},
				{
					"name": "Refresh Token",
					"event": [
						{
							"listen": "test",
							"script": {
								"exec": [
									"if (pm.response.code === 200) {",
									"    var jsonData = pm.response.json();",
									"    pm.collectionVariables.set(\"accessToken\", jsonData.accessToken);",
									"    pm.collectionVariables.set(\"refreshToken\", jsonData.refreshToken);",
									"}"
								],
								"type": "text/javascript"
							}
						}
					],
					"request": {
						"auth": {
							"type": "noauth"
						},
						"method": "POST",
						"header": [
							{
								"key": "Content-Type",
								"value": "application/json"
							}
						],
						"body": {
							"mode": "raw",
							"raw": "{\n    \"refreshToken\": \"{{refreshToken}}\"\n}"
						},
						"url": {
							"raw": "{{baseUrl}}/api/v1/auth/refresh",
							"host": [
								"{{baseUrl}}"
							],
							"path": [
								"api",
								"v1",
								"auth",
								"refresh"
							]
						},
						"description": "Renova o access token usando o refresh token"
					},
					"response": []
				}
			],
			"description": "Endpoints de autenticação e autorização"
		},
		{
			"name": "Tasklists",
			"item": [
				{
					"name": "Create Tasklist",
					"event": [
						{
							"listen": "test",
							"script": {
								"exec": [
									"if (pm.response.code === 201 || pm.response.code === 200) {",
									"    var jsonData = pm.response.json();",
									"    pm.collectionVariables.set(\"tasklistId\", jsonData.id);",
									"    console.log(\"Tasklist ID salvo: \" + jsonData.id);",
									"}"
								],
								"type": "text/javascript"
							}
						}
					],
					"request": {
						"method": "POST",
						"header": [
							{
								"key": "Content-Type",
								"value": "application/json"
							}
						],
						"body": {
							"mode": "raw",
							"raw": "{\n    \"name\": \"My Project Tasks\"\n}"
						},
						"url": {
							"raw": "{{baseUrl}}/api/v1/tasklists",
							"host": [
								"{{baseUrl}}"
							],
							"path": [
								"api",
								"v1",
								"tasklists"
							]
						},
						"description": "Cria uma nova lista de tarefas"
					},
					"response": []
				},
				{
					"name": "Get All Tasklists",
					"request": {
						"method": "GET",
						"header": [],
						"url": {
							"raw": "{{baseUrl}}/api/v1/tasklists",
							"host": [
								"{{baseUrl}}"
							],
							"path": [
								"api",
								"v1",
								"tasklists"
							]
						},
						"description": "Lista todas as tasklists do usuário autenticado"
					},
					"response": []
				},
				{
					"name": "Get Tasklist by ID",
					"request": {
						"method": "GET",
						"header": [],
						"url": {
							"raw": "{{baseUrl}}/api/v1/tasklists/{{tasklistId}}",
							"host": [
								"{{baseUrl}}"
							],
							"path": [
								"api",
								"v1",
								"tasklists",
								"{{tasklistId}}"
							]
						},
						"description": "Busca uma tasklist específica por ID"
					},
					"response": []
				},
				{
					"name": "Update Tasklist",
					"request": {
						"method": "PUT",
						"header": [
							{
								"key": "Content-Type",
								"value": "application/json"
							}
						],
						"body": {
							"mode": "raw",
							"raw": "{\n    \"name\": \"Updated Project Tasks\"\n}"
						},
						"url": {
							"raw": "{{baseUrl}}/api/v1/tasklists/{{tasklistId}}",
							"host": [
								"{{baseUrl}}"
							],
							"path": [
								"api",
								"v1",
								"tasklists",
								"{{tasklistId}}"
							]
						},
						"description": "Atualiza uma tasklist existente"
					},
					"response": []
				},
				{
					"name": "Delete Tasklist",
					"request": {
						"method": "DELETE",
						"header": [],
						"url": {
							"raw": "{{baseUrl}}/api/v1/tasklists/{{tasklistId}}",
							"host": [
								"{{baseUrl}}"
							],
							"path": [
								"api",
								"v1",
								"tasklists",
								"{{tasklistId}}"
							]
						},
						"description": "Deleta uma tasklist"
					},
					"response": []
				}
			],
			"description": "Endpoints para gerenciamento de tasklists"
		},
		{
			"name": "Tasks",
			"item": [
				{
					"name": "Create Task",
					"event": [
						{
							"listen": "test",
							"script": {
								"exec": [
									"if (pm.response.code === 201 || pm.response.code === 200) {",
									"    var jsonData = pm.response.json();",
									"    pm.collectionVariables.set(\"taskId\", jsonData.id);",
									"    console.log(\"Task ID salvo: \" + jsonData.id);",
									"}"
								],
								"type": "text/javascript"
							}
						}
					],
					"request": {
						"method": "POST",
						"header": [
							{
								"key": "Content-Type",
								"value": "application/json"
							}
						],
						"body": {
							"mode": "raw",
							"raw": "{\n    \"title\": \"Implement login feature\",\n    \"description\": \"Create login page with JWT authentication\",\n    \"status\": \"TODO\",\n    \"priority\": \"HIGH\",\n    \"tasklistId\": \"{{tasklistId}}\"\n}"
						},
						"url": {
							"raw": "{{baseUrl}}/api/v1/tasks",
							"host": [
								"{{baseUrl}}"
							],
							"path": [
								"api",
								"v1",
								"tasks"
							]
						},
						"description": "Cria uma nova tarefa"
					},
					"response": []
				},
				{
					"name": "Get All Tasks",
					"request": {
						"method": "GET",
						"header": [],
						"url": {
							"raw": "{{baseUrl}}/api/v1/tasks",
							"host": [
								"{{baseUrl}}"
							],
							"path": [
								"api",
								"v1",
								"tasks"
							]
						},
						"description": "Lista todas as tarefas do usuário autenticado"
					},
					"response": []
				},
				{
					"name": "Get Tasks by Tasklist",
					"request": {
						"method": "GET",
						"header": [],
						"url": {
							"raw": "{{baseUrl}}/api/v1/tasks/tasklist/{{tasklistId}}",
							"host": [
								"{{baseUrl}}"
							],
							"path": [
								"api",
								"v1",
								"tasks",
								"tasklist",
								"{{tasklistId}}"
							]
						},
						"description": "Lista todas as tarefas de uma tasklist específica"
					},
					"response": []
				},
				{
					"name": "Get Task by ID",
					"request": {
						"method": "GET",
						"header": [],
						"url": {
							"raw": "{{baseUrl}}/api/v1/tasks/{{taskId}}",
							"host": [
								"{{baseUrl}}"
							],
							"path": [
								"api",
								"v1",
								"tasks",
								"{{taskId}}"
							]
						},
						"description": "Busca uma tarefa específica por ID"
					},
					"response": []
				},
				{
					"name": "Update Task",
					"request": {
						"method": "PUT",
						"header": [
							{
								"key": "Content-Type",
								"value": "application/json"
							}
						],
						"body": {
							"mode": "raw",
							"raw": "{\n    \"title\": \"Updated task title\",\n    \"description\": \"Updated description\",\n    \"status\": \"IN_PROGRESS\",\n    \"priority\": \"MEDIUM\",\n    \"tasklistId\": \"{{tasklistId}}\"\n}"
						},
						"url": {
							"raw": "{{baseUrl}}/api/v1/tasks/{{taskId}}",
							"host": [
								"{{baseUrl}}"
							],
							"path": [
								"api",
								"v1",
								"tasks",
								"{{taskId}}"
							]
						},
						"description": "Atualiza uma tarefa existente"
					},
					"response": []
				},
				{
					"name": "Delete Task",
					"request": {
						"method": "DELETE",
						"header": [],
						"url": {
							"raw": "{{baseUrl}}/api/v1/tasks/{{taskId}}",
							"host": [
								"{{baseUrl}}"
							],
							"path": [
								"api",
								"v1",
								"tasks",
								"{{taskId}}"
							]
						},
						"description": "Deleta uma tarefa"
					},
					"response": []
				}
			],
			"description": "Endpoints para gerenciamento de tarefas"
		},
		{
			"name": "Health & Monitoring",
			"item": [
				{
					"name": "Health Check",
					"request": {
						"auth": {
							"type": "noauth"
						},
						"method": "GET",
						"header": [],
						"url": {
							"raw": "{{baseUrl}}/actuator/health",
							"host": [
								"{{baseUrl}}"
							],
							"path": [
								"actuator",
								"health"
							]
						},
						"description": "Verifica o status de saúde da aplicação"
					},
					"response": []
				},
				{
					"name": "Application Info",
					"request": {
						"auth": {
							"type": "noauth"
						},
						"method": "GET",
						"header": [],
						"url": {
							"raw": "{{baseUrl}}/actuator/info",
							"host": [
								"{{baseUrl}}"
							],
							"path": [
								"actuator",
								"info"
							]
						},
						"description": "Retorna informações sobre a aplicação"
					},
					"response": []
				}
			],
			"description": "Endpoints de monitoramento e health check"
		}
	],
	"variable": [
		{
			"key": "baseUrl",
			"value": "http://localhost:8080",
			"type": "string"
		},
		{
			"key": "accessToken",
			"value": "",
			"type": "string"
		},
		{
			"key": "refreshToken",
			"value": "",
			"type": "string"
		},
		{
			"key": "userId",
			"value": "",
			"type": "string"
		},
		{
			"key": "tasklistId",
			"value": "",
			"type": "string"
		},
		{
			"key": "taskId",
			"value": "",
			"type": "string"
		}
	]
}
